autosubmitAPIwu/__init__.py
autosubmitAPIwu/autosubmit.py
autosubmitAPIwu/fixHistoric.py
autosubmitAPIwu/fixHistoricEnergy.py
autosubmitAPIwu/populateComplete.py
autosubmitAPIwu/populateExperiment.py
autosubmitAPIwu/populateGraph.py
autosubmitAPIwu/populateTimes.py
autosubmitAPIwu/testAPI.py
autosubmitAPIwu/testEsarchive.py
autosubmitAPIwu/unofficialTest.py
autosubmitAPIwu/verifyComplete.py
autosubmitAPIwu/builders/__init__.py
autosubmitAPIwu/builders/basic_builder.py
autosubmitAPIwu/builders/configuration_facade_builder.py
autosubmitAPIwu/builders/experiment_history_builder.py
autosubmitAPIwu/builders/joblist_helper_builder.py
autosubmitAPIwu/builders/joblist_loader_builder.py
autosubmitAPIwu/builders/pkl_organizer_builder.py
autosubmitAPIwu/common/__init__.py
autosubmitAPIwu/common/utils.py
autosubmitAPIwu/common/utils_for_testing.py
autosubmitAPIwu/components/__init__.py
autosubmitAPIwu/components/experiment/__init__.py
autosubmitAPIwu/components/experiment/configuration_facade.py
autosubmitAPIwu/components/experiment/pkl_organizer.py
autosubmitAPIwu/components/experiment/test.py
autosubmitAPIwu/components/experiment/test_case/a29z/conf/autosubmit_a29z.conf
autosubmitAPIwu/components/experiment/test_case/a29z/conf/expdef_a29z.conf
autosubmitAPIwu/components/experiment/test_case/a29z/conf/jobs_a29z.conf
autosubmitAPIwu/components/experiment/test_case/a29z/conf/platforms_a29z.conf
autosubmitAPIwu/components/experiment/test_case/t0ni/conf/autosubmit_t0ni.conf
autosubmitAPIwu/components/experiment/test_case/t0ni/conf/expdef_t0ni.conf
autosubmitAPIwu/components/experiment/test_case/t0ni/conf/jobs_t0ni.conf
autosubmitAPIwu/components/experiment/test_case/t0ni/conf/platforms_t0ni.conf
autosubmitAPIwu/components/experiment/test_case/t0ni/conf/proj_t0ni.conf
autosubmitAPIwu/components/jobs/__init__.py
autosubmitAPIwu/components/jobs/job_factory.py
autosubmitAPIwu/components/jobs/job_support.py
autosubmitAPIwu/components/jobs/joblist_helper.py
autosubmitAPIwu-2.9.180.dist-info/LICENSE
autosubmitAPIwu-2.9.180.dist-info/METADATA
autosubmitAPIwu-2.9.180.dist-info/WHEEL
autosubmitAPIwu-2.9.180.dist-info/top_level.txt
autosubmitAPIwu-2.9.180.dist-info/RECORD
