Metadata-Version: 2.1
Name: autosubmitAPIwu
Version: 2.9.180
Summary: Autosubmit API: a versatile tool to manage Weather and Climate Experiments in diverse Supercomputing Environments. Now as an API that retrieves data from Autosubmit experiments.
Home-page: http://www.bsc.es/projects/earthscience/autosubmit/
Author: Domingo Manubens-Gil / Wilmer Uruchi
Author-email: domingo.manubens@bsc.es
License: GNU GPL v3
Download-URL: https://earth.bsc.es/wiki/doku.php?id=tools:autosubmit
Keywords: climate,weather,workflow,HPC,API
Platform: GNU/Linux Debian
Requires-Dist: argparse (<2,>=1.2)
Requires-Dist: python-dateutil (>2)
Requires-Dist: pydotplus (>=2)
Requires-Dist: pyparsing (>=2.0.1)
Requires-Dist: numpy
Requires-Dist: matplotlib
Requires-Dist: paramiko (==2.6.0)
Requires-Dist: mock (>=1.3.0)
Requires-Dist: portalocker (>=0.5.7)
Requires-Dist: networkx
Requires-Dist: bscearth.utils
Requires-Dist: Flask (==1.1.1)
Requires-Dist: Flask-Cors (==3.0.8)
Requires-Dist: Flask-Jsonpify (==1.5.0)
Requires-Dist: Flask-RESTful (==0.3.7)
Requires-Dist: SQLAlchemy (==1.3.6)
Requires-Dist: radical.saga (==0.70.0)
Requires-Dist: radical.utils (==0.70.0)
Provides-Extra: dialog
Requires-Dist: python2-pythondialog (>=3.3.0) ; extra == 'dialog'
